swarm_deploy/__init__.py
swarm_deploy/callable_name.py
swarm_deploy/main.py
swarm_deploy/message.py
swarm_deploy-0.0.4.dist-info/LICENSE
swarm_deploy-0.0.4.dist-info/METADATA
swarm_deploy-0.0.4.dist-info/WHEEL
swarm_deploy-0.0.4.dist-info/RECORD
