Metadata-Version: 2.1
Name: swarm-deploy
Version: 0.0.4
Summary: Swarm-Deploy - TGSC
Home-page: https://github.com/The-Swarm-Corporation/SwarmDeploy
License: MIT
Keywords: artificial intelligence,deep learning,optimizers,Prompt Engineering
Author: Kye Gomez
Author-email: kye@apac.ai
Requires-Python: >=3.10,<4.0
Classifier: Development Status :: 4 - Beta
Classifier: Intended Audience :: Developers
Classifier: License :: OSI Approved :: MIT License
Classifier: Programming Language :: Python :: 3
Classifier: Programming Language :: Python :: 3.10
Classifier: Programming Language :: Python :: 3.11
Classifier: Programming Language :: Python :: 3.12
Classifier: Programming Language :: Python :: 3.9
Classifier: Topic :: Scientific/Engineering :: Artificial Intelligence
Requires-Dist: aiocache
Requires-Dist: asyncio
Requires-Dist: datetime
Requires-Dist: fastapi
Requires-Dist: orjson
Requires-Dist: prometheus-client
Requires-Dist: pydantic
Requires-Dist: rich
Requires-Dist: structlog
Requires-Dist: swarms
Requires-Dist: typing
Requires-Dist: uuid
Project-URL: Documentation, https://github.com/The-Swarm-Corporation/SwarmDeploy
Project-URL: Repository, https://github.com/The-Swarm-Corporation/SwarmDeploy
